{"code": 0, "summary": {"cost": 5019, "unassigned": 2, "delivery": [33], "amount": [33], "pickup": [33], "service": 7920, "duration": 5019, "waiting_time": 0, "distance": 34831, "computing_times": {"loading": 496, "solving": 160, "routing": 322}}, "unassigned": [{"id": 65, "location": [-71.062547, 42.365557]}, {"id": 64, "location": [-71.061092, 42.351921]}], "routes": [{"vehicle": 0, "cost": 1921, "delivery": [11], "amount": [11], "pickup": [11], "service": 2640, "duration": 1921, "waiting_time": 0, "distance": 13781, "steps": [{"type": "start", "location": [-71.061033, 42.358157], "load": [0], "arrival": 1601566128, "duration": 0, "distance": 0}, {"type": "pickup", "location": [-71.05899, 42.356893], "id": 40, "service": 120, "waiting_time": 0, "job": 40, "load": [1], "arrival": 1601566200, "duration": 72, "distance": 553}, {"type": "pickup", "location": [-71.054213, 42.359051], "id": 38, "service": 120, "waiting_time": 0, "job": 38, "load": [2], "arrival": 1601566413, "duration": 165, "distance": 1172}, {"type": "pickup", "location": [-71.052605, 42.363441], "id": 34, "service": 120, "waiting_time": 0, "job": 34, "load": [3], "arrival": 1601566691, "duration": 323, "distance": 2363}, {"type": "pickup", "location": [-71.051368, 42.36385], "id": 32, "service": 120, "waiting_time": 0, "job": 32, "load": [4], "arrival": 1601566843, "duration": 355, "distance": 2541}, {"type": "pickup", "location": [-71.051368, 42.36385], "id": 46, "service": 120, "waiting_time": 0, "job": 46, "load": [5], "arrival": 1601566963, "duration": 355, "distance": 2541}, {"type": "pickup", "location": [-71.053035, 42.364949], "id": 56, "service": 120, "waiting_time": 0, "job": 56, "load": [6], "arrival": 1601567147, "duration": 419, "distance": 3111}, {"type": "pickup", "location": [-71.055473, 42.364678], "id": 52, "service": 120, "waiting_time": 0, "job": 52, "load": [7], "arrival": 1601567318, "duration": 470, "distance": 3461}, {"type": "pickup", "location": [-71.055976, 42.363235], "id": 10, "service": 120, "waiting_time": 0, "job": 10, "load": [8], "arrival": 1601567527, "duration": 559, "distance": 4042}, {"type": "pickup", "location": [-71.063149, 42.361016], "id": 22, "service": 120, "waiting_time": 0, "job": 22, "load": [9], "arrival": 1601567804, "duration": 716, "distance": 5076}, {"type": "pickup", "location": [-71.063035, 42.359924], "id": 2, "service": 120, "waiting_time": 0, "job": 2, "load": [10], "arrival": 1601567950, "duration": 742, "distance": 5240}, {"type": "delivery", "location": [-71.068816, 42.359775], "id": 33, "service": 120, "waiting_time": 0, "job": 33, "load": [9], "arrival": 1601568205, "duration": 877, "distance": 6043}, {"type": "delivery", "location": [-71.067973, 42.364229], "id": 47, "service": 120, "waiting_time": 0, "job": 47, "load": [8], "arrival": 1601568458, "duration": 1010, "distance": 6784}, {"type": "delivery", "location": [-71.068738, 42.364504], "id": 41, "service": 120, "waiting_time": 0, "job": 41, "load": [7], "arrival": 1601568604, "duration": 1036, "distance": 6918}, {"type": "delivery", "location": [-71.059874, 42.365502], "id": 39, "service": 120, "waiting_time": 0, "job": 39, "load": [6], "arrival": 1601568844, "duration": 1156, "distance": 8150}, {"type": "delivery", "location": [-71.059874, 42.365502], "id": 53, "service": 120, "waiting_time": 0, "job": 53, "load": [5], "arrival": 1601568964, "duration": 1156, "distance": 8150}, {"type": "pickup", "location": [-71.059402, 42.364849], "id": 0, "service": 120, "waiting_time": 0, "job": 0, "load": [6], "arrival": 1601569087, "duration": 1159, "distance": 8231}, {"type": "delivery", "location": [-71.05901, 42.363772], "id": 1, "service": 120, "waiting_time": 0, "job": 1, "load": [5], "arrival": 1601569384, "duration": 1336, "distance": 9851}, {"type": "delivery", "location": [-71.060397, 42.364138], "id": 23, "service": 120, "waiting_time": 0, "job": 23, "load": [4], "arrival": 1601569530, "duration": 1362, "distance": 9993}, {"type": "delivery", "location": [-71.064164, 42.363163], "id": 35, "service": 120, "waiting_time": 0, "job": 35, "load": [3], "arrival": 1601569753, "duration": 1465, "distance": 10504}, {"type": "delivery", "location": [-71.06453, 42.360252], "id": 3, "service": 120, "waiting_time": 0, "job": 3, "load": [2], "arrival": 1601569960, "duration": 1552, "distance": 11117}, {"type": "delivery", "location": [-71.062455, 42.351805], "id": 57, "service": 120, "waiting_time": 0, "job": 57, "load": [1], "arrival": 1601570290, "duration": 1762, "distance": 12630}, {"type": "delivery", "location": [-71.055274, 42.356693], "id": 11, "service": 120, "waiting_time": 0, "job": 11, "load": [0], "arrival": 1601570569, "duration": 1921, "distance": 13781}], "geometry": "oapaGlbvpLVwA@CDUBOb@aCRiABIl@mDDSUWYY@KF[DgA?W?ON?rBER@L@?N@rAAn@?PMn@Yz@ELDMX{@Lo@?Q@o@AsA?OAQE}A?QAGAg@ASCWAMG{@AQAKIY_@{@O]Ua@EGIMq@eAGKEEk@_AGMKOoAsBGKINi@`AMTIJSL_@NOFOF@d@Dv@@PJCn@Wj@UHEFCt@[l@WJG@ALGKOoAsBGKEK]yDCUEa@AQGq@CUWDa@H{AXUDUFg@Pk@Vw@f@a@`@IHMJSXSZKNe@`AINa@~@_@|@w@nBCH[x@KROKWQc@k@WS[OWMMI_@YIIEGc@g@GOE[OwBCm@E_@AOGc@Qg@EGFG^a@n@q@@EBKIGYOs@SKOCQCWo@@Y?O?M?m@?SAG?e@?E?_BFO@cADo@NG@YL[JQFBd@VvE@PF@ZDj@JD@^HLD`@JJBNFLDJFJFJFf@d@HHDDlAlAFFBBx@|@HJv@|@FFKFaAlBQj@?H?FI?e@Ak@CSAK?w@Eg@AHO`DyGFMBBx@|@HJv@|@FFFFf@d@p@l@d@b@RVPRZ`@DFJNMTGPa@v@ABE@SEGCKI]QKIQIIGc@WCDo@hCCH@b@BjA?F?B@J@t@@NYXSLs@t@MLEDIDIBOBODQFLDn@F\\?`ACN?BJDJt@tAJP`AhBFF@BJFJn@BNTpAPz@F^FX^hBLd@HXh@dADFPTn@h@VNPFDBf@PRH@d@?P?zA?`@XIAW?g@Ao@?S?c@V?h@AhDCN?O?iDBi@@W?WC@d@?P?zA?`@@d@@rA@`@BbB@~A?n@?nB@lA?F?R?T?X@vC@jA?z@?F@\\TDL?dCMH?FA~AGd@CH??K?qC?SAQCoC?OI@eCHG@I?gCFK@USQ?_D@O?I?U@sA@_CBO@e@@YLONGNGTCR?TARCpAAn@Ir@CPWjBMCs@Sr@RLBUxAALCROGwAw@wAm@[K_@c@[a@Y]o@u@U]Qk@AIAOCc@?SB]VuBTeBD]B{@G{@I_@K[Q[SWWOyCyAa@a@We@W}@Im@Ao@D_ABQFU^oA`@y@f@y@zDuFpAwA|@}@tBsB`DcD????xD_Cp@e@n@q@rAuBn@kAn@y@Te@Pg@Hg@HeA@iA@g@Bg@Hu@La@NYRURORCNFFFJY^y@DKJQMMk@k@MGKCKNe@`AINa@~@_@|@w@nBCH[x@KRKVOZy@hBIRMTGPa@v@ABu@~ACDQXININMPOTo@r@URYXSLs@t@MLEDIDIBOBODQFLDn@F\\?`ACN?BJDJt@tAINONwBfCKJHNl@fAJRDHDJt@tADHGJyEnFGFGHIDJX`@bAf@lA`@VZ?R@N@NDJDVJXJJD\\LAFCPKr@PFQGJs@BQ@GVHpATTBF?F@F?z@@TAN?vCONA@d@@rA@`@BbB@~ATAAw@?O?WA_BNAbDObDON?D?jD?H?JvB?D@JF?v@@`A?tA?D?L?CKSuAmA}FIWJIDCb@]f@i@zBeCDEPSd@j@xB|BHJ\\\\v@p@JHTNz@`@|CnAdBj@LB`AZl@H`@H^HD@RDNBz@Nt@L@WHcAL_CPoC@QIAKAo@MOCkASSCC]KqCAe@AGAQ?OAa@AMEoAAu@?s@@_@@c@@u@@I@O?OTaDDk@@g@ASUAs@IcBMIGGGIQCSFUBQF_@D_@@EBSBMECMQa@aAISCEIUGMs@sBQ]QYaBiBKMMMs@w@c@g@CEKIIHg@f@MN{A~AIHIHYXeAhA"}, {"vehicle": 1, "cost": 1941, "delivery": [11], "amount": [11], "pickup": [11], "service": 2640, "duration": 1941, "waiting_time": 0, "distance": 13392, "steps": [{"type": "start", "location": [-71.061033, 42.358157], "load": [0], "arrival": 1601566112, "duration": 0, "distance": 0}, {"type": "pickup", "location": [-71.063149, 42.361016], "id": 30, "service": 120, "waiting_time": 0, "job": 30, "load": [1], "arrival": 1601566200, "duration": 88, "distance": 589}, {"type": "pickup", "location": [-71.06011, 42.357712], "id": 48, "service": 120, "waiting_time": 0, "job": 48, "load": [2], "arrival": 1601566404, "duration": 172, "distance": 1167}, {"type": "pickup", "location": [-71.058394, 42.3576], "id": 20, "service": 120, "waiting_time": 0, "job": 20, "load": [3], "arrival": 1601566543, "duration": 191, "distance": 1327}, {"type": "pickup", "location": [-71.05899, 42.356893], "id": 8, "service": 120, "waiting_time": 0, "job": 8, "load": [4], "arrival": 1601566704, "duration": 232, "distance": 1629}, {"type": "pickup", "location": [-71.061753, 42.351651], "id": 18, "service": 120, "waiting_time": 0, "job": 18, "load": [5], "arrival": 1601566992, "duration": 400, "distance": 2711}, {"type": "pickup", "location": [-71.061753, 42.351651], "id": 66, "service": 120, "waiting_time": 0, "job": 66, "load": [6], "arrival": 1601567112, "duration": 400, "distance": 2711}, {"type": "pickup", "location": [-71.061753, 42.351651], "id": 58, "service": 120, "waiting_time": 0, "job": 58, "load": [7], "arrival": 1601567232, "duration": 400, "distance": 2711}, {"type": "pickup", "location": [-71.062616, 42.351688], "id": 62, "service": 120, "waiting_time": 0, "job": 62, "load": [8], "arrival": 1601567369, "duration": 417, "distance": 2812}, {"type": "pickup", "location": [-71.0466, 42.352161], "id": 28, "service": 120, "waiting_time": 0, "job": 28, "load": [9], "arrival": 1601567722, "duration": 650, "distance": 4450}, {"type": "pickup", "location": [-71.0466, 42.352161], "id": 50, "service": 120, "waiting_time": 0, "job": 50, "load": [10], "arrival": 1601567842, "duration": 650, "distance": 4450}, {"type": "delivery", "location": [-71.053059, 42.353652], "id": 31, "service": 120, "waiting_time": 0, "job": 31, "load": [9], "arrival": 1601568116, "duration": 804, "distance": 5538}, {"type": "delivery", "location": [-71.055274, 42.356693], "id": 67, "service": 120, "waiting_time": 0, "job": 67, "load": [8], "arrival": 1601568290, "duration": 858, "distance": 5931}, {"type": "delivery", "location": [-71.064164, 42.363163], "id": 19, "service": 120, "waiting_time": 0, "job": 19, "load": [7], "arrival": 1601568586, "duration": 1034, "distance": 7182}, {"type": "pickup", "location": [-71.063149, 42.361016], "id": 60, "service": 120, "waiting_time": 0, "job": 60, "load": [8], "arrival": 1601568747, "duration": 1075, "distance": 7520}, {"type": "delivery", "location": [-71.066617, 42.358269], "id": 49, "service": 120, "waiting_time": 0, "job": 49, "load": [7], "arrival": 1601568978, "duration": 1186, "distance": 8146}, {"type": "delivery", "location": [-71.066617, 42.358269], "id": 51, "service": 120, "waiting_time": 0, "job": 51, "load": [6], "arrival": 1601569098, "duration": 1186, "distance": 8146}, {"type": "delivery", "location": [-71.068144, 42.349945], "id": 59, "service": 120, "waiting_time": 0, "job": 59, "load": [5], "arrival": 1601569448, "duration": 1416, "distance": 9707}, {"type": "delivery", "location": [-71.068487, 42.350048], "id": 29, "service": 120, "waiting_time": 0, "job": 29, "load": [4], "arrival": 1601569590, "duration": 1438, "distance": 9828}, {"type": "delivery", "location": [-71.067146, 42.349509], "id": 63, "service": 120, "waiting_time": 0, "job": 63, "load": [3], "arrival": 1601569745, "duration": 1473, "distance": 10023}, {"type": "delivery", "location": [-71.067715, 42.348715], "id": 9, "service": 120, "waiting_time": 0, "job": 9, "load": [2], "arrival": 1601569896, "duration": 1504, "distance": 10197}, {"type": "delivery", "location": [-71.062455, 42.351805], "id": 61, "service": 120, "waiting_time": 0, "job": 61, "load": [1], "arrival": 1601570119, "duration": 1607, "distance": 10921}, {"type": "delivery", "location": [-71.068807, 42.359604], "id": 21, "service": 120, "waiting_time": 0, "job": 21, "load": [0], "arrival": 1601570573, "duration": 1941, "distance": 13392}], "geometry": "oapaGlbvpLKn@G^ALQ?oA@aAHMHEDDj@@f@Dr@@PFPHnAaAEGBEFEHCNDz@@f@K?sBFu@DwCNM@AW?g@Ao@?S?c@@g@B_ABYD]BWF[R_AHc@Ne@b@iA^m@^e@f@e@r@_@v@Wp@Gp@?H?PDj@PRJB@XR@@nAx@JFBOReAN{@RiABIl@mDDSQSCCYY@KF[DgA?W?ON?rBER@L@?N@rAAn@?PMn@Yz@ELDMX{@Lo@?Q@o@AsA?OLBzABlCEL@JBRDXLHFL^pDzDHBHDHFh@l@nApAJLLJ@?RD`AKPNDNA`@sAnDEJEJo@~AIPJFd@JN@fACb@APCNCj@Il@IvASHB?R@zA?@@lAERO|ACNUEi@KkASSCC]KqCAe@AGAQ?OAa@AMEoAAu@?s@@_@@c@@u@@I@O?OTaDDk@@g@ASJQRy@PkABQAU@Wj@uDDWOIIC[OoAq@KGOMKK_@c@U_@{@wBYq@c@iAKYQc@o@_BIQGOiAsCO_@a@cAKWNSJMRW`@o@HQ`EaKZ{@BGLUHENW\\kAdB{EJWHW@ClAgDL_@QMK^c@dAi@xAADKVKZgAxC_@dA[~@GVAL@NJDj@`@xCtBbAr@RNr@d@NLDDe@v@CFEJCDS`@GTe@~AW|@{@rCADELCFCDEFQLOP_DdDi@l@EBQRQc@Se@[y@IQMLYXe@d@QPMLuBnBIHIHg@f@MN{A~AIHIHYXeAhACBm@l@IJKJqBlBIHI@I@KB{@PMDcARaAROB@RAZ?@@VBlB?F?NAN]fCADS~@I`@CLQn@AHCFMZSPK@WFs@Vk@\\_@V_A~@Wb@Q`@Sh@Qb@Md@Q|@U~AGxA?d@@d@?P?zA?`@O@wCNO?U@{@AG?GAG?UCqAUWIAFCPKr@PFQGJs@BQ@GVHpATTBF?F@F?z@@TAN?vCONAXIAW?g@Ao@?S?c@V?h@AhDClAAPHHN@PDz@@f@?DBhAB|@@FDND?jD?H?JvB?D@J?J?jCDjA?JDv@@JAKEw@JCpA]xCy@JEBL`@tCTbBRpA@H@F@Lz@jGBT@Z@FBLBVBHLj@DNz@nG@FDZb@`CBNFVHLNDJ?RA^Mz@]DAJElAe@`A_@BCLE`@QTILEJEv@[PGx@]DALEjAe@r@[DAVONGp@W\\Mf@QDCTIJCpCy@XI`@M~@YCWe@aFMcAGk@GBy@R@FLvA@Hb@IXEFAUoBSoBj@c@h@m@Tj@z@bCZ`A@FDAXKPINKRODEEKMWS_@a@{@[o@q@qAKUa@DKBI@eEh@_@HKBC[Mw@Gc@AOCO?QFwD?_@BID_@BeAFeBHyBBc@OKGGA?ICmASGCIAKAo@MOCkASSCOAoBGK?UAG?g@MiAm@GG_@]IIw@s@CHy@bBc@fAw@tBITTNz@`@|CnAdBj@LB`AZl@H`@H^HD@RDADCXWfICrBALE`@ETSXYVQPcAd@oCpAyEtBcAd@i@TMJw@f@KJG\\Ab@@Nz@nG@FDZb@`CPpABDDT@T@TITKJeAb@I@IAQOKG_@OUGOC}Cm@MEWGa@G]DiEw@yA[m@I?SAeCAwA?G?UASA{A?MAKAaA?KCoD"}, {"vehicle": 2, "cost": 1157, "delivery": [11], "amount": [11], "pickup": [11], "service": 2640, "duration": 1157, "waiting_time": 0, "distance": 7658, "steps": [{"type": "start", "location": [-71.061033, 42.358157], "load": [0], "arrival": 1601566192, "duration": 0, "distance": 0}, {"type": "pickup", "location": [-71.06011, 42.357712], "id": 6, "service": 120, "waiting_time": 0, "job": 6, "load": [1], "arrival": 1601566204, "duration": 12, "distance": 91}, {"type": "pickup", "location": [-71.058947, 42.351125], "id": 4, "service": 120, "waiting_time": 0, "job": 4, "load": [2], "arrival": 1601566523, "duration": 211, "distance": 1473}, {"type": "pickup", "location": [-71.060954, 42.351578], "id": 44, "service": 120, "waiting_time": 0, "job": 44, "load": [3], "arrival": 1601566748, "duration": 316, "distance": 2029}, {"type": "pickup", "location": [-71.063011, 42.351362], "id": 14, "service": 120, "waiting_time": 0, "job": 14, "load": [4], "arrival": 1601566911, "duration": 359, "distance": 2316}, {"type": "pickup", "location": [-71.05899, 42.356893], "id": 36, "service": 120, "waiting_time": 0, "job": 36, "load": [5], "arrival": 1601567143, "duration": 471, "distance": 3209}, {"type": "pickup", "location": [-71.051401, 42.36024], "id": 26, "service": 120, "waiting_time": 0, "job": 26, "load": [6], "arrival": 1601567393, "duration": 601, "distance": 4050}, {"type": "pickup", "location": [-71.051401, 42.36024], "id": 54, "service": 120, "waiting_time": 0, "job": 54, "load": [7], "arrival": 1601567513, "duration": 601, "distance": 4050}, {"type": "pickup", "location": [-71.053738, 42.364642], "id": 24, "service": 120, "waiting_time": 0, "job": 24, "load": [8], "arrival": 1601567739, "duration": 707, "distance": 4888}, {"type": "pickup", "location": [-71.053738, 42.364642], "id": 16, "service": 120, "waiting_time": 0, "job": 16, "load": [9], "arrival": 1601567859, "duration": 707, "distance": 4888}, {"type": "delivery", "location": [-71.052468, 42.365058], "id": 37, "service": 120, "waiting_time": 0, "job": 37, "load": [8], "arrival": 1601568000, "duration": 728, "distance": 5034}, {"type": "delivery", "location": [-71.051793, 42.363939], "id": 45, "service": 120, "waiting_time": 0, "job": 45, "load": [7], "arrival": 1601568150, "duration": 758, "distance": 5201}, {"type": "delivery", "location": [-71.051793, 42.363939], "id": 5, "service": 120, "waiting_time": 0, "job": 5, "load": [6], "arrival": 1601568270, "duration": 758, "distance": 5201}, {"type": "pickup", "location": [-71.055976, 42.363235], "id": 12, "service": 120, "waiting_time": 0, "job": 12, "load": [7], "arrival": 1601568498, "duration": 866, "distance": 5930}, {"type": "pickup", "location": [-71.055976, 42.363235], "id": 42, "service": 120, "waiting_time": 0, "job": 42, "load": [8], "arrival": 1601568618, "duration": 866, "distance": 5930}, {"type": "delivery", "location": [-71.05593, 42.364475], "id": 15, "service": 120, "waiting_time": 0, "job": 15, "load": [7], "arrival": 1601568767, "duration": 895, "distance": 6093}, {"type": "delivery", "location": [-71.05593, 42.364475], "id": 55, "service": 120, "waiting_time": 0, "job": 55, "load": [6], "arrival": 1601568887, "duration": 895, "distance": 6093}, {"type": "delivery", "location": [-71.057085, 42.36452], "id": 25, "service": 120, "waiting_time": 0, "job": 25, "load": [5], "arrival": 1601569024, "duration": 912, "distance": 6187}, {"type": "delivery", "location": [-71.057085, 42.36452], "id": 17, "service": 120, "waiting_time": 0, "job": 17, "load": [4], "arrival": 1601569144, "duration": 912, "distance": 6187}, {"type": "delivery", "location": [-71.05901, 42.363772], "id": 13, "service": 120, "waiting_time": 0, "job": 13, "load": [3], "arrival": 1601569321, "duration": 969, "distance": 6502}, {"type": "delivery", "location": [-71.059171, 42.365347], "id": 43, "service": 120, "waiting_time": 0, "job": 43, "load": [2], "arrival": 1601569629, "duration": 1157, "distance": 7658}, {"type": "delivery", "location": [-71.059171, 42.365347], "id": 27, "service": 120, "waiting_time": 0, "job": 27, "load": [1], "arrival": 1601569749, "duration": 1157, "distance": 7658}, {"type": "delivery", "location": [-71.059171, 42.365347], "id": 7, "service": 120, "waiting_time": 0, "job": 7, "load": [0], "arrival": 1601569869, "duration": 1157, "distance": 7658}], "geometry": "oapaGlbvpLVwA@CDUBOReAN{@RiABIl@mDDSUWYY@KF[DgA?W?ON?rBER@L@LBzABlCEL@JBRDXLHFL^pDzDHBHDHFh@l@nApAJLLJ@?RD`AKf@ED?J??OTaDDk@@g@ASJQRy@PkABQRDdALTBdD`@LBEVYfBO~@EZEZSpAIEIGWMQKMIMIIIIIY[GG?Hj@p@v@d@`@LHBEZCXNDnBl@d@LXHEZGVQn@]nBCJQE}@YuAa@KCU~AAF?JAPLDJBhAZ\\HVHD@HBCPYlBAJEVGTId@Et@ARGGA?ICw@OUCGCIAKA_AQkASSCC]KqCAe@AGAQ?OAa@OEi@Q{@w@GGMKaAy@KIgCqCQYOg@CSGY{@cAi@k@EE}@{@GGQUEEQIq@QMCYC{BJI?An@?PMn@Yz@ELDMX{@Lo@?Q@o@AsA?OAQE}A?QAGAg@ASCWAMG{@AQAKIY_@{@O]Ua@EGIMq@eAGKEEk@_AGMKOoAsBGKEK]yDCUEa@AQGq@CUWDa@H{AXUDCWMsAC][BZCB\\LrABVUFg@Pk@Vw@f@a@`@IHMJSXSZKNe@`AINa@~@_@|@w@nBCH[x@KRKVOZy@hBIRKOEG[a@QSSWe@c@q@m@g@e@GGGGw@}@IKy@}@CCGGm@m@_@_@EEIIg@e@KGKGKGMEBS\\iB\\qBBOZ?lB?H?F@VDNFNH^ZFJFG^a@n@q@@EBKFDbAz@FDRPvBfBLLLHdCtBHFa@~@_@|@w@nBCH[x@KRKVOZy@hBIRMTGPa@v@ABE@SEGCKI]QKIQIIGc@WKGKGa@UGCGC_@OI?e@AADIhACZANCj@@z@?d@@f@@b@@J?LDhA?LBr@@VEDIDIBOBODQFLDn@F\\?`ACN?BJDJt@tAINONwBfCKJGKo@mAIHeEzEIHQc@ISKMOKRUxDoENQNOr@y@XQXM`ACN?NALCPGLCHEXSlAsAV]BCPUGSSm@KOUOYMAREV_@j@_BbBe@\\a@Vm@b@aAt@_BzAML"}]}