{"code": 0, "summary": {"cost": 4434, "unassigned": 14, "delivery": [23], "amount": [23], "pickup": [23], "service": 8280, "duration": 4434, "waiting_time": 95, "distance": 31040, "computing_times": {"loading": 342, "solving": 114, "routing": 251}}, "unassigned": [{"id": 39, "location": [-71.059874, 42.365502]}, {"id": 38, "location": [-71.05899, 42.356893]}, {"id": 2, "location": [-71.052614, 42.363455]}, {"id": 3, "location": [-71.059874, 42.365502]}, {"id": 18, "location": [-71.05899, 42.356893]}, {"id": 19, "location": [-71.059168, 42.352118]}, {"id": 20, "location": [-71.062616, 42.351688]}, {"id": 21, "location": [-71.067257, 42.358909]}, {"id": 24, "location": [-71.059402, 42.364849]}, {"id": 25, "location": [-71.059171, 42.365347]}, {"id": 26, "location": [-71.051401, 42.36024]}, {"id": 27, "location": [-71.05901, 42.363772]}, {"id": 32, "location": [-71.063035, 42.359924]}, {"id": 33, "location": [-71.063099, 42.3516]}], "routes": [{"vehicle": 0, "cost": 1153, "delivery": [9], "amount": [9], "pickup": [9], "service": 3240, "duration": 1153, "waiting_time": 2, "distance": 8868, "steps": [{"type": "start", "location": [-71.061033, 42.358157], "load": [0], "arrival": 1601566184, "duration": 0, "distance": 0}, {"type": "pickup", "location": [-71.065163, 42.351324], "id": 52, "service": 180, "waiting_time": 0, "job": 52, "load": [1], "arrival": 1601566295, "duration": 111, "distance": 899}, {"type": "pickup", "location": [-71.061753, 42.351651], "id": 42, "service": 180, "waiting_time": 0, "job": 42, "load": [2], "arrival": 1601566563, "duration": 199, "distance": 1471}, {"type": "pickup", "location": [-71.062616, 42.351688], "id": 30, "service": 180, "waiting_time": 0, "job": 30, "load": [3], "arrival": 1601566760, "duration": 216, "distance": 1572}, {"type": "pickup", "location": [-71.062616, 42.351688], "id": 36, "service": 180, "waiting_time": 0, "job": 36, "load": [4], "arrival": 1601566940, "duration": 216, "distance": 1572}, {"type": "pickup", "location": [-71.062616, 42.351688], "id": 12, "service": 180, "waiting_time": 0, "job": 12, "load": [5], "arrival": 1601567120, "duration": 216, "distance": 1572}, {"type": "pickup", "location": [-71.051401, 42.36024], "id": 0, "service": 180, "waiting_time": 0, "job": 0, "load": [6], "arrival": 1601567513, "duration": 429, "distance": 3097}, {"type": "pickup", "location": [-71.063149, 42.361016], "id": 44, "service": 180, "waiting_time": 0, "job": 44, "load": [7], "arrival": 1601567876, "duration": 612, "distance": 4344}, {"type": "delivery", "location": [-71.064164, 42.363163], "id": 13, "service": 180, "waiting_time": 0, "job": 13, "load": [6], "arrival": 1601568112, "duration": 668, "distance": 4731}, {"type": "delivery", "location": [-71.068738, 42.364504], "id": 43, "service": 180, "waiting_time": 0, "job": 43, "load": [5], "arrival": 1601568428, "duration": 804, "distance": 5522}, {"type": "delivery", "location": [-71.068738, 42.364504], "id": 37, "service": 180, "waiting_time": 0, "job": 37, "load": [4], "arrival": 1601568608, "duration": 804, "distance": 5522}, {"type": "delivery", "location": [-71.059874, 42.365502], "id": 1, "service": 180, "waiting_time": 0, "job": 1, "load": [3], "arrival": 1601568908, "duration": 924, "distance": 6753}, {"type": "delivery", "location": [-71.059874, 42.365502], "id": 45, "service": 180, "waiting_time": 0, "job": 45, "load": [2], "arrival": 1601569088, "duration": 924, "distance": 6753}, {"type": "delivery", "location": [-71.059874, 42.365502], "id": 53, "service": 180, "waiting_time": 0, "job": 53, "load": [1], "arrival": 1601569268, "duration": 924, "distance": 6753}, {"type": "pickup", "location": [-71.051368, 42.36385], "id": 8, "service": 180, "waiting_time": 0, "job": 8, "load": [2], "arrival": 1601569584, "duration": 1060, "distance": 8060}, {"type": "pickup", "location": [-71.051368, 42.36385], "id": 40, "service": 180, "waiting_time": 0, "job": 40, "load": [3], "arrival": 1601569764, "duration": 1060, "distance": 8060}, {"type": "delivery", "location": [-71.052189, 42.366511], "id": 9, "service": 180, "waiting_time": 0, "job": 9, "load": [2], "arrival": 1601569985, "duration": 1101, "distance": 8438}, {"type": "delivery", "location": [-71.05488, 42.363287], "id": 31, "service": 180, "waiting_time": 0, "job": 31, "load": [1], "arrival": 1601570217, "duration": 1153, "distance": 8868}, {"type": "delivery", "location": [-71.05488, 42.363287], "id": 41, "service": 180, "waiting_time": 2, "job": 41, "load": [0], "arrival": 1601570397, "duration": 1153, "distance": 8867}], "geometry": "oapaGlbvpLVwA@CDUFDTR|B|BHH~AfBPPBBLNd@j@xB|BHJ\\\\v@p@JHTNz@`@|CnAdBj@LB`AZl@H`@H^HD@RDNBz@Nt@LJBVBt@NNDXFBID_@BeAFeBHyBBc@@WFaB?WDW@KXmBBQBKXgBBKQE}@YuAa@KCWfB?JAP?R@zA?@@lAERO|ACNUEi@KkASSCC]KqCAe@AGAQ?OAa@OEi@Q{@w@GGMKaAy@KIgCqCQYOg@CSGY{@cAi@k@EE}@{@GGQUEEQIq@QMCYC{BJI?AsA?OAQE}A?QAGAg@ASCWAMG{@AQAKIY_@{@O]Ua@EGIMq@eAGKEEk@_AGMKOoAsBGKEK]yDCUEa@AQGq@CUWDa@H{AXUDCWMsAC][BZCB\\LrABV@XHfAD\\BVZ|CBX@PHr@Dr@@d@Dv@@PBPLtAHz@@LJz@@LVlC?DBZ@RAZ?@@VBlB?F?NAN]fCADS~@I`@CLQn@AHCFMZSPK@WFs@Vk@\\_@V_A~@Wb@Q`@Sh@Qb@Md@Q|@U~AGxA?d@@d@?P?zA?`@XIAW?g@Ao@?S?c@WC@d@?P?zA?`@O@wCNO?U@{@AG?GAG?UCqAUWIAFCPKr@PFQGJs@BQ@GVHpATTBF?F@F?z@@TA?^?Jc@|DEJIDc@?a@CE?s@EQBEFCH_@lCAn@@tA?j@?XO@e@@YLONGNGTCR?TARE`CIr@CPWjBMCs@Sr@RLBUxAALCROGwAw@wAm@[K_@c@[a@Y]o@u@U]Qk@AIAOCc@?SB]VuBTeBD]B{@G{@I_@K[Q[SWWOyCyAa@a@We@W}@Im@Ao@D_ABQFU^oA`@y@f@y@zDuFpAwA|@}@vGwG????xD_Cp@e@n@q@rAuBn@kAn@y@Te@Pg@Hg@HeA@iA@g@Bg@Hu@La@NYRURORCNFFFJY^y@DKJQMMk@k@MGKCOOsAiA]k@Qa@AGAEo@cBW_@WYMGGVO`@mAfBGJGEcA{@GEIGYOs@SKOCQCWo@@Y?O?M?m@?SAG?e@?E?_BFO@cADo@NG@YL[JQFBd@JnBJfB@PF@ZDj@JD@^HLD`@JJBNFLDJFJFJFf@d@HHDDlAlAFFBBx@|@HJv@|@FFFFf@d@LL"}, {"vehicle": 1, "cost": 1529, "delivery": [7], "amount": [7], "pickup": [7], "service": 2520, "duration": 1529, "waiting_time": 44, "distance": 9949, "steps": [{"type": "start", "location": [-71.061033, 42.358157], "load": [0], "arrival": 1601566193, "duration": 0, "distance": 0}, {"type": "pickup", "location": [-71.063149, 42.361016], "id": 10, "service": 180, "waiting_time": 0, "job": 10, "load": [1], "arrival": 1601566281, "duration": 88, "distance": 589}, {"type": "pickup", "location": [-71.06011, 42.357712], "id": 6, "service": 180, "waiting_time": 0, "job": 6, "load": [2], "arrival": 1601566545, "duration": 172, "distance": 1167}, {"type": "pickup", "location": [-71.063011, 42.351362], "id": 4, "service": 180, "waiting_time": 0, "job": 4, "load": [3], "arrival": 1601566902, "duration": 349, "distance": 2422}, {"type": "pickup", "location": [-71.063011, 42.351362], "id": 14, "service": 180, "waiting_time": 0, "job": 14, "load": [4], "arrival": 1601567082, "duration": 349, "distance": 2422}, {"type": "pickup", "location": [-71.051401, 42.36024], "id": 58, "service": 180, "waiting_time": 0, "job": 58, "load": [5], "arrival": 1601567480, "duration": 567, "distance": 3989}, {"type": "pickup", "location": [-71.055473, 42.364678], "id": 34, "service": 180, "waiting_time": 0, "job": 34, "load": [6], "arrival": 1601567773, "duration": 680, "distance": 4810}, {"type": "pickup", "location": [-71.053738, 42.364642], "id": 48, "service": 180, "waiting_time": 0, "job": 48, "load": [7], "arrival": 1601567998, "duration": 725, "distance": 5071}, {"type": "delivery", "location": [-71.056111, 42.36449], "id": 15, "service": 180, "waiting_time": 0, "job": 15, "load": [6], "arrival": 1601568224, "duration": 771, "distance": 5374}, {"type": "delivery", "location": [-71.05676, 42.364896], "id": 35, "service": 180, "waiting_time": 0, "job": 35, "load": [5], "arrival": 1601568458, "duration": 825, "distance": 5672}, {"type": "delivery", "location": [-71.05676, 42.364896], "id": 11, "service": 180, "waiting_time": 0, "job": 11, "load": [4], "arrival": 1601568638, "duration": 825, "distance": 5672}, {"type": "delivery", "location": [-71.067973, 42.364229], "id": 49, "service": 180, "waiting_time": 0, "job": 49, "load": [3], "arrival": 1601569051, "duration": 1058, "distance": 7130}, {"type": "delivery", "location": [-71.06453, 42.360252], "id": 5, "service": 180, "waiting_time": 0, "job": 5, "load": [2], "arrival": 1601569384, "duration": 1211, "distance": 7914}, {"type": "delivery", "location": [-71.063615, 42.36052], "id": 7, "service": 180, "waiting_time": 44, "job": 7, "load": [1], "arrival": 1601569712, "duration": 1359, "distance": 8862}, {"type": "delivery", "location": [-71.056111, 42.36449], "id": 59, "service": 180, "waiting_time": 0, "job": 59, "load": [0], "arrival": 1601570106, "duration": 1529, "distance": 9949}], "geometry": "oapaGlbvpLKn@G^ALQ?oA@aAHMHEDDj@@f@Dr@@PFPHnAaAEGBEFEHCNDz@@f@K?sBFu@DwCNM@AW?g@Ao@?S?c@@g@B_ABYD]BWF[R_AHc@Ne@b@iA^m@^e@f@e@r@_@v@Wp@Gp@?H?PDj@PRJB@XR@@nAx@JFBOReAN{@RiAFDfBzAn@j@\\XFFQd@cAxCEL~AfBPPBBLNd@j@xB|BHJ\\\\v@p@JHTNz@`@|CnAdBj@LB`AZl@H`@H^HD@RDNBz@Nt@LJBVBdATXFBID_@BeAFeBHyBBc@OKGGA?ICw@OUCGCIAKA_AQkASSCC]KqCAe@AGAQ?OAa@OEi@Q{@w@GGMKaAy@KIgCqCQYOg@CSGY{@cAi@k@EE}@{@GGQUEEQIq@QMCYC{BJI?AsA?OAQE}A?QAGAg@ASCWAMG{@AQAKIY_@{@O]Ua@EGIMq@eAGKEEk@_AGMKOoAsBGKEK]yDCUEa@AQGq@CUWDa@H{AXUDCWMsAC][BZCB\\LrABVUFg@Pk@Vw@f@a@`@IHMJSXSZKNe@`AINa@~@_@|@w@nBCH[x@KRKVOZy@hBIRMTGPa@v@ABE@SEGCKI]Q]SIGc@WKGKGa@UGCGC_@OI?e@Ak@CSAK?w@Eg@AHO`DyGFMGGm@m@l@l@FFBBx@|@HJv@|@FFKFaAlBQj@?H?FI?e@AADMdB?DAHCj@@z@?d@BjA@JI?a@DsAHe@@I??MCcB?MDAnAElAGH??d@BjA@J?LDhA?LBr@@VEDIDIBOBODQFLDn@F\\?`ACN?BJDJt@tAJP`AhBFF@BJFJn@BNTpAPz@F^FX^hBLd@HXh@dADFPTn@h@VNPFDBf@PRH@d@?P?zA?`@O@wCNO??^?Jc@|DEJIDc@?a@CE?s@EQBEFCH_@lCAn@@tA?j@?XO@e@@YLONGNGTCR?TARCpAAn@Ir@CPPDD[Fm@DwB@Y?W@QDOPUVK`@CL?~BChBCJ?N?|CCP?TA?]Ay@?[?kA?}@?a@Aw@?O?WA_BNAbDObDON?D?jD?H?JvB?D@JF?v@@`A?tA?D?L?CKSuAmA}FIWK]W}@GEQAmBZI@G@G@k@BQ?aAEGBEFEHCNDz@@f@K?sBFu@Dc@BsBJM@AW?g@AcA?c@WCSIg@QECQGWOo@i@QUEGi@eAIYMe@_@iBGYG_@Q{@UqACORqAHc@F_@b@mAR]@?RYK[I]e@sBI[GSSm@KOUOYMININAWB_@BOr@yABEKI]Q]SIGc@WKGKGa@UGCGC_@OI?e@AADMdB?D"}, {"vehicle": 2, "cost": 1752, "delivery": [7], "amount": [7], "pickup": [7], "service": 2520, "duration": 1752, "waiting_time": 49, "distance": 12223, "steps": [{"type": "start", "location": [-71.061033, 42.358157], "load": [0], "arrival": 1601566197, "duration": 0, "distance": 0}, {"type": "pickup", "location": [-71.063035, 42.359924], "id": 46, "service": 180, "waiting_time": 0, "job": 46, "load": [1], "arrival": 1601566242, "duration": 45, "distance": 320}, {"type": "pickup", "location": [-71.055473, 42.364678], "id": 22, "service": 180, "waiting_time": 0, "job": 22, "load": [2], "arrival": 1601566589, "duration": 212, "distance": 1392}, {"type": "pickup", "location": [-71.052614, 42.363455], "id": 16, "service": 180, "waiting_time": 0, "job": 16, "load": [3], "arrival": 1601566951, "duration": 394, "distance": 2427}, {"type": "pickup", "location": [-71.052605, 42.363441], "id": 56, "service": 180, "waiting_time": 0, "job": 56, "load": [4], "arrival": 1601567131, "duration": 394, "distance": 2427}, {"type": "pickup", "location": [-71.063011, 42.351362], "id": 50, "service": 180, "waiting_time": 0, "job": 50, "load": [5], "arrival": 1601567639, "duration": 722, "distance": 4802}, {"type": "pickup", "location": [-71.061092, 42.351921], "id": 28, "service": 180, "waiting_time": 0, "job": 28, "load": [6], "arrival": 1601567858, "duration": 761, "distance": 5093}, {"type": "pickup", "location": [-71.061753, 42.351651], "id": 54, "service": 180, "waiting_time": 0, "job": 54, "load": [7], "arrival": 1601568059, "duration": 782, "distance": 5207}, {"type": "delivery", "location": [-71.068487, 42.350048], "id": 29, "service": 180, "waiting_time": 0, "job": 29, "load": [6], "arrival": 1601568420, "duration": 963, "distance": 6487}, {"type": "delivery", "location": [-71.068487, 42.350048], "id": 47, "service": 180, "waiting_time": 0, "job": 47, "load": [5], "arrival": 1601568600, "duration": 963, "distance": 6487}, {"type": "delivery", "location": [-71.068487, 42.350048], "id": 51, "service": 180, "waiting_time": 0, "job": 51, "load": [4], "arrival": 1601568780, "duration": 963, "distance": 6487}, {"type": "delivery", "location": [-71.071952, 42.355671], "id": 57, "service": 180, "waiting_time": 0, "job": 57, "load": [3], "arrival": 1601569118, "duration": 1121, "distance": 7656}, {"type": "delivery", "location": [-71.059168, 42.352118], "id": 55, "service": 180, "waiting_time": 0, "job": 55, "load": [2], "arrival": 1601569494, "duration": 1317, "distance": 9103}, {"type": "delivery", "location": [-71.067146, 42.349509], "id": 23, "service": 180, "waiting_time": 0, "job": 23, "load": [1], "arrival": 1601569881, "duration": 1524, "distance": 10640}, {"type": "delivery", "location": [-71.073223, 42.353937], "id": 17, "service": 180, "waiting_time": 49, "job": 17, "load": [0], "arrival": 1601570289, "duration": 1752, "distance": 12222}], "geometry": "oapaGlbvpLKn@G^ALQ?oA@aAHMHEDDj@@f@Dr@@PALEb@GNKDa@?g@L}@@O?iDBi@@W?WCSIg@QECQGWOo@i@QUEGi@eAIYMe@_@iBGYG_@Q{@UqACORqAHc@F_@b@mAR]@?RYK[I]e@sBI[GSSm@KOUOYMININAWB_@BOr@yABEKI]Q]SIGc@WKGKGa@UGCGC_@OI?e@Ak@CSAK?w@Eg@AHO`DyGFMGGmAmAEEDONg@Jc@j@aC`@_BBOF@VD^P^ZFJFG^a@n@q@@EBKFDbAz@FDRPvBfBLLEH]l@EHW`@EHIJ_AnAQXg@r@KJEGc@g@GOE[OwBCm@C]AAAOGc@Qg@EGFG^a@n@q@@EBKFDbAz@FDFKlAgBNa@FWLFVXV^n@bB@D@FP`@\\j@rAhANNDNHJNNZ\\JLJQV]RUJKDCl@c@`A_@REVGFAtAY`@GTGRC~Be@VGFC`Bm@VGZIp@IPCPA|@?x@Jt@TXNt@l@LNLLZd@`@x@x@zBHTHRVj@DLVj@@FJTJXRl@`CnFRXVTNZDHN^FJNl@x@vENr@HRFTFPJXHNJRn@z@f@h@n@b@t@\\NDNDnBl@d@LXHEZGVQn@]nBCJCJYfBCJCPYlBAJEVGTId@Et@ARGGA?ICw@OUCGCIAKA_AQkASSCC]KqCAe@AGAQNCj@Il@IC[?C?BBZvASHB?R@zA?@@lAJ?pAETHDBJBEVGTId@Et@ARAXYfH?ZBTBJ?^GvD?PBN@NFb@?t@APENEFy@Z[Jw@VAL?XDbAJrADZBNRhB@N^`DFPn@z@JLJCpCy@XI`@M~@YCWe@aFUoBGBy@R@FLvA@Hb@IXEFAUoBSoBj@c@h@m@CSEa@BWI@eEh@_@HKB_@Jy@Z[Jw@VgA^u@PODMBo@PS@cAd@oCpAyEtBcAd@i@TMJw@f@KJG\\Ab@@Nz@nG@FDZZhBFVBNFVHLNDJ?RA^Mz@]DAJElAe@`A_@BCLE`@QTILEJEv@[PGx@]DALEjAe@r@[DAVOAUQaAg@eECOE]OuAAKM_AUwBASAc@AmABsBVgIBY@E@KBc@@c@@o@?Y@Q?c@A_@KsB?ICWC]KqCAe@AGAQ?OAa@AMEoAAu@?s@@_@@c@@u@@I@OLAbAGp@GFBXRHL?D?DCLIH{CXKA@u@@I@O?OTaDDQDIHCH?JHJRn@z@f@h@n@b@t@\\NDNDnBl@d@LXHEZGVQn@]nBCJCJYfBCJCPYlBAJEVGTId@Et@ARAXYfH?ZBTBJTFNBv@NhAVpB\\VB^FzBXD?PBAZUdDARIKOG]GWAy@Ha@DKBCVD`@BRTj@z@bCZ`A@FDAXKPINKRODEEKa@w@a@{@[o@q@qAKUa@DKBI@eEh@_@HKB_@Jy@Z[Jw@VgA^u@PODMBo@PS@cAd@oCpAyEtBcAd@i@TMJw@f@KJG\\Ab@@Nz@nG@FDZb@`CBNFVHLNDJ?RA^Mz@]DAJElAe@DT`ArF"}]}