{"code": 0, "summary": {"cost": 2875, "unassigned": 0, "delivery": [21], "amount": [21], "pickup": [21], "service": 5040, "duration": 2875, "waiting_time": 0, "distance": 19438, "computing_times": {"loading": 255, "solving": 68, "routing": 258}}, "unassigned": [], "routes": [{"vehicle": 0, "cost": 1395, "delivery": [10], "amount": [10], "pickup": [10], "service": 2400, "duration": 1395, "waiting_time": 0, "distance": 9944, "steps": [{"type": "start", "location": [-71.061033, 42.358157], "load": [0], "arrival": 1601566216, "duration": 0, "distance": 0}, {"type": "pickup", "location": [-71.065163, 42.351324], "id": 8, "service": 120, "waiting_time": 0, "job": 8, "load": [1], "arrival": 1601566327, "duration": 111, "distance": 899}, {"type": "pickup", "location": [-71.062616, 42.351688], "id": 40, "service": 120, "waiting_time": 0, "job": 40, "load": [2], "arrival": 1601566490, "duration": 154, "distance": 1175}, {"type": "pickup", "location": [-71.062616, 42.351688], "id": 0, "service": 120, "waiting_time": 0, "job": 0, "load": [3], "arrival": 1601566610, "duration": 154, "distance": 1175}, {"type": "pickup", "location": [-71.05899, 42.356893], "id": 36, "service": 120, "waiting_time": 0, "job": 36, "load": [4], "arrival": 1601566837, "duration": 261, "distance": 2026}, {"type": "pickup", "location": [-71.05899, 42.356893], "id": 16, "service": 120, "waiting_time": 0, "job": 16, "load": [5], "arrival": 1601566957, "duration": 261, "distance": 2026}, {"type": "pickup", "location": [-71.058394, 42.3576], "id": 14, "service": 120, "waiting_time": 0, "job": 14, "load": [6], "arrival": 1601567089, "duration": 273, "distance": 2099}, {"type": "pickup", "location": [-71.051401, 42.36024], "id": 18, "service": 120, "waiting_time": 0, "job": 18, "load": [7], "arrival": 1601567327, "duration": 391, "distance": 2883}, {"type": "pickup", "location": [-71.055976, 42.363235], "id": 28, "service": 120, "waiting_time": 0, "job": 28, "load": [8], "arrival": 1601567530, "duration": 474, "distance": 3537}, {"type": "pickup", "location": [-71.055473, 42.364678], "id": 32, "service": 120, "waiting_time": 0, "job": 32, "load": [9], "arrival": 1601567680, "duration": 504, "distance": 3703}, {"type": "pickup", "location": [-71.055473, 42.364678], "id": 20, "service": 120, "waiting_time": 0, "job": 20, "load": [10], "arrival": 1601567800, "duration": 504, "distance": 3703}, {"type": "delivery", "location": [-71.051793, 42.363939], "id": 15, "service": 120, "waiting_time": 0, "job": 15, "load": [9], "arrival": 1601568000, "duration": 584, "distance": 4169}, {"type": "delivery", "location": [-71.051793, 42.363939], "id": 19, "service": 120, "waiting_time": 0, "job": 19, "load": [8], "arrival": 1601568120, "duration": 584, "distance": 4169}, {"type": "delivery", "location": [-71.051793, 42.363939], "id": 1, "service": 120, "waiting_time": 0, "job": 1, "load": [7], "arrival": 1601568240, "duration": 584, "distance": 4169}, {"type": "delivery", "location": [-71.052189, 42.366511], "id": 29, "service": 120, "waiting_time": 0, "job": 29, "load": [6], "arrival": 1601568432, "duration": 656, "distance": 4716}, {"type": "delivery", "location": [-71.05187, 42.365655], "id": 41, "service": 120, "waiting_time": 0, "job": 41, "load": [5], "arrival": 1601568577, "duration": 681, "distance": 4895}, {"type": "delivery", "location": [-71.05488, 42.363287], "id": 33, "service": 120, "waiting_time": 0, "job": 33, "load": [4], "arrival": 1601568752, "duration": 736, "distance": 5314}, {"type": "delivery", "location": [-71.066617, 42.358269], "id": 9, "service": 120, "waiting_time": 0, "job": 9, "load": [3], "arrival": 1601569123, "duration": 987, "distance": 6954}, {"type": "delivery", "location": [-71.067533, 42.349334], "id": 17, "service": 120, "waiting_time": 0, "job": 17, "load": [2], "arrival": 1601569475, "duration": 1219, "distance": 8755}, {"type": "delivery", "location": [-71.067533, 42.349334], "id": 21, "service": 120, "waiting_time": 0, "job": 21, "load": [1], "arrival": 1601569595, "duration": 1219, "distance": 8755}, {"type": "delivery", "location": [-71.060518, 42.351787], "id": 37, "service": 120, "waiting_time": 0, "job": 37, "load": [0], "arrival": 1601569891, "duration": 1395, "distance": 9944}], "geometry": "oapaGlbvpLVwA@CDUFDTR|B|BHH~AfBPPBBLNd@j@xB|BHJ\\\\v@p@JHTNz@`@|CnAdBj@LB`AZl@H`@H^HD@RDNBz@Nt@LJBVBt@NNDXFBID_@BeAFeBHyBBc@OKGGA?ICmASGCIAKAUEi@KkASSCC]KqCAe@AGAQ?OAa@OEi@Q{@w@GGMKaAy@KIgCqCQYOg@CSGY{@cAi@k@EE}@{@GGQUEEQIq@QMCYC{BJI?An@?PMn@Yz@ELMKaA_AGGQSCCYY@KF[DgA?W?O?M?{A?y@?SAMg@sDAOCIM[GO@IBKJa@X_ADMEEk@_AGMKOoAsBGKEK]yDCUEa@AQGq@CUWDa@H{AXUDCWMsAC][BZCB\\LrABVUFg@Pk@Vw@f@a@`@IHMJSXSZKNe@`AINa@~@_@|@w@nBCH[x@KRKVOZy@hBIRMTGPa@v@ABE@SEGCKI]QKIQIIGc@WKGKGa@UGCGC_@OI?e@Ak@CSAK?w@Eg@AHO`DyGFMGGmAmAEEDONg@Jc@j@aC`@_BBOF@VDNFNH^ZFJFG^a@n@q@@EBKIGYOs@SKOCQCWo@@Y?O?M?m@?SAG?e@?E?_BFO@cADo@NG@YL[JQFBd@JnBKoBCe@PGZKXMLXBDv@f@AJGf@CTAZAz@KhAEPD@^HLD`@JJBNFLDJFJFJFf@d@HHDDlAlAFFBBx@|@HJv@|@FFFFf@d@LLb@^d@b@RVPRZ`@DFJNMTGPa@v@ABu@~ACDQXININMPOTo@r@URYXSLs@t@MLEDIDIBOBODQFLDn@F\\?`ACN?BJDJt@tAJP`AhBFF@BJFJn@BNTpAPz@F^FX^hBLd@HXh@dADFPTn@h@VNPFDBf@PRHVBV?h@AhDClAAPHHN@PDz@@f@?DBhAB|@@FDND?jD?H?JvB?D@J?J?jCDjA?JDv@@JAKEw@JCpA]xCy@JEE]WgB?ECKSuAmA}FIWJIDCb@]f@i@zBeCDEPSd@j@xB|BHJ\\\\v@p@JHTNz@`@|CnAdBj@LB`AZl@H`@H^HD@RDNBz@Nt@LJBVBdATXFTFNBv@NhAVpB\\VB^FzBXD?PBAZUdDARIKOG]GWAy@Ha@DKBCVD`@BRv@xBXt@Z`A@FDAXKPINKRODEEKa@w@a@{@[o@q@qAKUa@DKBI@eEh@_@HKBC[Mw@Gc@AOCO?QFwD?_@BID_@BeAFeBHyBBc@@WFaB?WDW@KXmBBQBKXgBBKBK\\oBGAcDcAKCQrAMBsAV"}, {"vehicle": 1, "cost": 383, "delivery": [2], "amount": [2], "pickup": [2], "service": 480, "duration": 383, "waiting_time": 0, "distance": 2277, "steps": [{"type": "start", "location": [-71.061033, 42.358157], "load": [0], "arrival": 1601567552, "duration": 0, "distance": 0}, {"type": "pickup", "location": [-71.063149, 42.361016], "id": 30, "service": 120, "waiting_time": 0, "job": 30, "load": [1], "arrival": 1601567640, "duration": 88, "distance": 589}, {"type": "pickup", "location": [-71.063149, 42.361016], "id": 2, "service": 120, "waiting_time": 0, "job": 2, "load": [2], "arrival": 1601567760, "duration": 88, "distance": 589}, {"type": "delivery", "location": [-71.067973, 42.364229], "id": 31, "service": 120, "waiting_time": 0, "job": 31, "load": [1], "arrival": 1601568000, "duration": 208, "distance": 1283}, {"type": "delivery", "location": [-71.069467, 42.359204], "id": 3, "service": 120, "waiting_time": 0, "job": 3, "load": [0], "arrival": 1601568295, "duration": 383, "distance": 2277}], "geometry": "oapaGlbvpLKn@G^ALQ?oA@aAHMHEDDj@@f@Dr@@PFPHnAaAEGBEFEHCNDz@@f@K?sBFu@DwCNM@AW?g@Ao@?S?c@WC@d@?P?zA?`@O@wCNO??^?Jc@|DEJIDc@?a@CE?s@EQBEFCH_@lCAn@@tA?j@?XO@e@@YLONGNGTCR?TARCpAAn@Ir@CPPDD[Fm@DwB@Y?W@QDOPUVK`@CL?~BChBCJ?N?|CCP??X@vC@jA?z@?F@\\TDL?dCMH??LBlB?nA@v@?Hh@BdBLJ?AKAaAD?j@G@KAa@"}, {"vehicle": 2, "cost": 1097, "delivery": [9], "amount": [9], "pickup": [9], "service": 2160, "duration": 1097, "waiting_time": 0, "distance": 7217, "steps": [{"type": "start", "location": [-71.061033, 42.358157], "load": [0], "arrival": 1601566604, "duration": 0, "distance": 0}, {"type": "pickup", "location": [-71.063035, 42.359924], "id": 26, "service": 120, "waiting_time": 0, "job": 26, "load": [1], "arrival": 1601566649, "duration": 45, "distance": 320}, {"type": "pickup", "location": [-71.058394, 42.3576], "id": 12, "service": 120, "waiting_time": 0, "job": 12, "load": [2], "arrival": 1601566892, "duration": 168, "distance": 1176}, {"type": "pickup", "location": [-71.048774, 42.351209], "id": 6, "service": 120, "waiting_time": 0, "job": 6, "load": [3], "arrival": 1601567203, "duration": 359, "distance": 2422}, {"type": "pickup", "location": [-71.052614, 42.363455], "id": 22, "service": 120, "waiting_time": 0, "job": 22, "load": [4], "arrival": 1601567565, "duration": 601, "distance": 4221}, {"type": "pickup", "location": [-71.052605, 42.363441], "id": 4, "service": 120, "waiting_time": 0, "job": 4, "load": [5], "arrival": 1601567685, "duration": 601, "distance": 4221}, {"type": "pickup", "location": [-71.051368, 42.36385], "id": 10, "service": 120, "waiting_time": 0, "job": 10, "load": [6], "arrival": 1601567837, "duration": 633, "distance": 4400}, {"type": "delivery", "location": [-71.05187, 42.365655], "id": 13, "service": 120, "waiting_time": 0, "job": 13, "load": [5], "arrival": 1601568000, "duration": 676, "distance": 4746}, {"type": "delivery", "location": [-71.052189, 42.366511], "id": 11, "service": 120, "waiting_time": 0, "job": 11, "load": [4], "arrival": 1601568147, "duration": 703, "distance": 4927}, {"type": "delivery", "location": [-71.052189, 42.366511], "id": 5, "service": 120, "waiting_time": 0, "job": 5, "load": [3], "arrival": 1601568267, "duration": 703, "distance": 4927}, {"type": "pickup", "location": [-71.053738, 42.364642], "id": 34, "service": 120, "waiting_time": 0, "job": 34, "load": [4], "arrival": 1601568417, "duration": 733, "distance": 5179}, {"type": "pickup", "location": [-71.055473, 42.364678], "id": 24, "service": 120, "waiting_time": 0, "job": 24, "load": [5], "arrival": 1601568581, "duration": 777, "distance": 5470}, {"type": "pickup", "location": [-71.055473, 42.364678], "id": 38, "service": 120, "waiting_time": 0, "job": 38, "load": [6], "arrival": 1601568701, "duration": 777, "distance": 5470}, {"type": "delivery", "location": [-71.05676, 42.364896], "id": 25, "service": 120, "waiting_time": 0, "job": 25, "load": [5], "arrival": 1601568957, "duration": 913, "distance": 6255}, {"type": "delivery", "location": [-71.05676, 42.364896], "id": 35, "service": 120, "waiting_time": 0, "job": 35, "load": [4], "arrival": 1601569077, "duration": 913, "distance": 6255}, {"type": "delivery", "location": [-71.057908, 42.364472], "id": 27, "service": 120, "waiting_time": 0, "job": 27, "load": [3], "arrival": 1601569224, "duration": 940, "distance": 6403}, {"type": "delivery", "location": [-71.05901, 42.363772], "id": 23, "service": 120, "waiting_time": 0, "job": 23, "load": [2], "arrival": 1601569389, "duration": 985, "distance": 6651}, {"type": "delivery", "location": [-71.062645, 42.364532], "id": 39, "service": 120, "waiting_time": 0, "job": 39, "load": [1], "arrival": 1601569621, "duration": 1097, "distance": 7217}, {"type": "delivery", "location": [-71.062645, 42.364532], "id": 7, "service": 120, "waiting_time": 0, "job": 7, "load": [0], "arrival": 1601569741, "duration": 1097, "distance": 7217}], "geometry": "oapaGlbvpLKn@G^ALQ?oA@aAHMHEDDj@@f@Dr@@PALEb@GNKDa@?g@L}@@O?iDBi@@W?@g@B_ABYD]BWF[R_AHc@Ne@b@iA^m@^e@f@e@r@_@v@Wp@Gp@?H?PDj@PRJB@XR@@nAx@JFBOb@aCRiABIl@mDDSQSCCYY@KF[DgA?W?ON?rBER@L@AQE}A?QAGAg@ASLC@ALCf@Mb@Kt@WLIPKb@c@HIFGfCqC`@a@FGHIPSNQn@s@DCLORS`@a@PSDENQPSDCh@m@~CeDNQPMDGBEBGDM@Ez@sCV}@d@_BFURa@BEDKBGd@w@HMNYnA}BEEw@i@IIGHGJa@r@s@pAEHSOcAs@yCuBk@a@KEMTCF[z@aE`KIPa@n@SVKLORQ[UW_@SIEKCWGg@I_AMwBQg@?K?{@@g@Ja@RaA`AMFOFOBq@HyAVSBWDa@H{AXUDUFg@Pk@Vw@f@a@`@IHMJSXSZKNe@`AINa@~@_@|@w@nBCH[x@KROKWQc@k@WS[OWMMI_@YIIEGc@g@GOE[OwBCm@C]AAAOGc@Qg@EGFG^a@n@q@@EBKIGYOs@SKOCQCWo@@Y?O?M?m@?SAG?e@?E?_BFO@cADo@NG@LXBDv@f@AJGf@CTAZAz@KhAEPk@K[EGAAQKgBJfB@PF@ZDj@JD@^HLD`@JJBNFLDJFJFJFf@d@HHDD^^l@l@FFBBx@|@HJv@|@FFKFaAlBQj@?H?FI?e@Ak@CSAK?w@Eg@AHO`DyGFMBBx@|@HJv@|@FFKFaAlBQj@?H?FI?e@AADMdBANCj@@z@?d@BjA@JI?a@DsAHe@@I??MCcB?MDAnAElAGH??d@BjA@J?LDhA?L@L@d@@VEDIDIBOBODQFLDn@F\\?`ACN?BJDJt@tAINONwBfCKJHNx@zADHDJt@tADHGJyEnFGFGHIDJX`@bAf@lA`@VE[GQYo@Sc@"}]}